[
  {
    "date": "2025-12-17",
    "price": 880,
    "sales_point": 102,
    "rating": null,
    "rating_count": null,
    "review_count": null
  },
  {
    "date": "2025-12-18",
    "price": 880,
    "sales_point": 160,
    "rating": null,
    "rating_count": null,
    "review_count": null
  },
  {
    "date": "2025-12-19",
    "price": 880,
    "sales_point": 188,
    "rating": null,
    "rating_count": null,
    "review_count": null
  },
  {
    "date": "2025-12-20",
    "price": 880,
    "sales_point": 212,
    "rating": null,
    "rating_count": null,
    "review_count": null
  },
  {
    "date": "2025-12-21",
    "price": 880,
    "sales_point": 238,
    "rating": null,
    "rating_count": null,
    "review_count": null
  },
  {
    "date": "2025-12-22",
    "price": 880,
    "sales_point": 247,
    "rating": null,
    "rating_count": null,
    "review_count": null
  },
  {
    "date": "2025-12-23",
    "price": 880,
    "sales_point": 251,
    "rating": null,
    "rating_count": null,
    "review_count": null
  },
  {
    "date": "2025-12-24",
    "price": 880,
    "sales_point": 256,
    "rating": null,
    "rating_count": null,
    "review_count": null
  },
  {
    "date": "2025-12-25",
    "price": 880,
    "sales_point": 259,
    "rating": null,
    "rating_count": null,
    "review_count": null
  },
  {
    "date": "2025-12-26",
    "price": 880,
    "sales_point": 261,
    "rating": null,
    "rating_count": null,
    "review_count": null
  },
  {
    "date": "2025-12-27",
    "price": 880,
    "sales_point": 269,
    "rating": null,
    "rating_count": null,
    "review_count": null
  },
  {
    "date": "2025-12-28",
    "price": 880,
    "sales_point": 273,
    "rating": null,
    "rating_count": null,
    "review_count": null
  },
  {
    "date": "2025-12-29",
    "price": 880,
    "sales_point": 275,
    "rating": null,
    "rating_count": null,
    "review_count": null
  },
  {
    "date": "2025-12-30",
    "price": 880,
    "sales_point": 278,
    "rating": null,
    "rating_count": null,
    "review_count": null
  },
  {
    "date": "2025-12-31",
    "price": 880,
    "sales_point": 290,
    "rating": null,
    "rating_count": null,
    "review_count": null
  },
  {
    "date": "2026-01-01",
    "price": 880,
    "sales_point": 296,
    "rating": null,
    "rating_count": null,
    "review_count": null
  },
  {
    "date": "2026-01-02",
    "price": 880,
    "sales_point": 299,
    "rating": 4.5,
    "rating_count": 20,
    "review_count": 0
  },
  {
    "date": "2026-01-03",
    "price": 880,
    "sales_point": 300,
    "rating": 4.39,
    "rating_count": 23,
    "review_count": 0
  },
  {
    "date": "2026-01-04",
    "price": 880,
    "sales_point": 305,
    "rating": 4.39,
    "rating_count": 23,
    "review_count": 0
  },
  {
    "date": "2026-01-05",
    "price": 880,
    "sales_point": 308,
    "rating": 4.39,
    "rating_count": 23,
    "review_count": 0
  },
  {
    "date": "2026-01-06",
    "price": 880,
    "sales_point": 312,
    "rating": 4.39,
    "rating_count": 23,
    "review_count": 0
  },
  {
    "date": "2026-01-07",
    "price": 880,
    "sales_point": 313,
    "rating": 4.39,
    "rating_count": 23,
    "review_count": 0
  },
  {
    "date": "2026-01-08",
    "price": 880,
    "sales_point": 313,
    "rating": 4.39,
    "rating_count": 23,
    "review_count": 0
  },
  {
    "date": "2026-01-09",
    "price": 880,
    "sales_point": 314,
    "rating": 4.39,
    "rating_count": 23,
    "review_count": 0
  },
  {
    "date": "2026-01-10",
    "price": 880,
    "sales_point": 317,
    "rating": 4.42,
    "rating_count": 24,
    "review_count": 0
  },
  {
    "date": "2026-01-11",
    "price": 880,
    "sales_point": 318,
    "rating": 4.42,
    "rating_count": 24,
    "review_count": 0
  },
  {
    "date": "2026-01-12",
    "price": 880,
    "sales_point": 320,
    "rating": 4.42,
    "rating_count": 24,
    "review_count": 0
  },
  {
    "date": "2026-01-13",
    "price": 880,
    "sales_point": 320,
    "rating": 4.42,
    "rating_count": 24,
    "review_count": 0
  },
  {
    "date": "2026-01-14",
    "price": 880,
    "sales_point": 320,
    "rating": 4.42,
    "rating_count": 24,
    "review_count": 0
  },
  {
    "date": "2026-01-15",
    "price": 880,
    "sales_point": 321,
    "rating": 4.42,
    "rating_count": 24,
    "review_count": 0
  },
  {
    "date": "2026-01-16",
    "price": 880,
    "sales_point": 322,
    "rating": 4.42,
    "rating_count": 24,
    "review_count": 0
  },
  {
    "date": "2026-01-17",
    "price": 880,
    "sales_point": 326,
    "rating": 4.4,
    "rating_count": 25,
    "review_count": 0
  },
  {
    "date": "2026-01-18",
    "price": 880,
    "sales_point": 327,
    "rating": 4.4,
    "rating_count": 25,
    "review_count": 0
  },
  {
    "date": "2026-01-19",
    "price": 880,
    "sales_point": 330,
    "rating": 4.4,
    "rating_count": 25,
    "review_count": 0
  },
  {
    "date": "2026-01-20",
    "price": 880,
    "sales_point": 330,
    "rating": 4.4,
    "rating_count": 25,
    "review_count": 0
  },
  {
    "date": "2026-01-21",
    "price": 880,
    "sales_point": 330,
    "rating": 4.4,
    "rating_count": 25,
    "review_count": 0
  },
  {
    "date": "2026-01-22",
    "price": 880,
    "sales_point": 331,
    "rating": 4.4,
    "rating_count": 25,
    "review_count": 0
  },
  {
    "date": "2026-01-23",
    "price": 880,
    "sales_point": 332,
    "rating": 4.4,
    "rating_count": 25,
    "review_count": 0
  },
  {
    "date": "2026-01-24",
    "price": 880,
    "sales_point": 332,
    "rating": 4.4,
    "rating_count": 25,
    "review_count": 0
  },
  {
    "date": "2026-01-25",
    "price": 880,
    "sales_point": 333,
    "rating": 4.44,
    "rating_count": 27,
    "review_count": 0
  },
  {
    "date": "2026-01-26",
    "price": 880,
    "sales_point": 334,
    "rating": 4.44,
    "rating_count": 27,
    "review_count": 0
  },
  {
    "date": "2026-01-27",
    "price": 880,
    "sales_point": 336,
    "rating": 4.44,
    "rating_count": 27,
    "review_count": 0
  },
  {
    "date": "2026-01-28",
    "price": 880,
    "sales_point": 338,
    "rating": 4.46,
    "rating_count": 28,
    "review_count": 0
  },
  {
    "date": "2026-01-29",
    "price": 880,
    "sales_point": 340,
    "rating": 4.46,
    "rating_count": 28,
    "review_count": 0
  },
  {
    "date": "2026-01-30",
    "price": 880,
    "sales_point": 344,
    "rating": 4.46,
    "rating_count": 28,
    "review_count": 0
  },
  {
    "date": "2026-01-31",
    "price": 880,
    "sales_point": 349,
    "rating": 4.5,
    "rating_count": 30,
    "review_count": 0
  },
  {
    "date": "2026-02-01",
    "price": 880,
    "sales_point": 357,
    "rating": 4.52,
    "rating_count": 31,
    "review_count": 0
  },
  {
    "date": "2026-02-02",
    "price": 880,
    "sales_point": 358,
    "rating": 4.52,
    "rating_count": 31,
    "review_count": 0
  },
  {
    "date": "2026-02-03",
    "price": 880,
    "sales_point": 358,
    "rating": 4.53,
    "rating_count": 32,
    "review_count": 0
  },
  {
    "date": "2026-02-04",
    "price": 440,
    "sales_point": 370,
    "rating": 4.53,
    "rating_count": 34,
    "review_count": 0
  },
  {
    "date": "2026-02-05",
    "price": 440,
    "sales_point": 384,
    "rating": 4.5,
    "rating_count": 36,
    "review_count": 0
  },
  {
    "date": "2026-02-06",
    "price": 440,
    "sales_point": 399,
    "rating": 4.5,
    "rating_count": 40,
    "review_count": 0
  },
  {
    "date": "2026-02-07",
    "price": 440,
    "sales_point": 417,
    "rating": 4.52,
    "rating_count": 42,
    "review_count": 0
  },
  {
    "date": "2026-02-08",
    "price": 440,
    "sales_point": 434,
    "rating": 4.52,
    "rating_count": 42,
    "review_count": 0
  },
  {
    "date": "2026-02-09",
    "price": 440,
    "sales_point": 445,
    "rating": 4.5,
    "rating_count": 44,
    "review_count": 0
  },
  {
    "date": "2026-02-10",
    "price": 440,
    "sales_point": 450,
    "rating": 4.49,
    "rating_count": 45,
    "review_count": 0
  }
]