[
  {
    "date": "2026-04-21",
    "price": 990,
    "sales_point": 425,
    "rating": 4.93,
    "rating_count": 15,
    "review_count": 0
  },
  {
    "date": "2026-04-22",
    "price": 990,
    "sales_point": 769,
    "rating": 4.9,
    "rating_count": 21,
    "review_count": 0
  },
  {
    "date": "2026-04-23",
    "price": 990,
    "sales_point": 978,
    "rating": 4.86,
    "rating_count": 22,
    "review_count": 0
  },
  {
    "date": "2026-04-24",
    "price": 990,
    "sales_point": 1126,
    "rating": 4.89,
    "rating_count": 27,
    "review_count": 0
  },
  {
    "date": "2026-04-25",
    "price": 990,
    "sales_point": 1267,
    "rating": 4.88,
    "rating_count": 34,
    "review_count": 0
  },
  {
    "date": "2026-04-26",
    "price": 990,
    "sales_point": 1390,
    "rating": 4.89,
    "rating_count": 36,
    "review_count": 0
  },
  {
    "date": "2026-04-27",
    "price": 990,
    "sales_point": 1445,
    "rating": 4.9,
    "rating_count": 40,
    "review_count": 0
  },
  {
    "date": "2026-04-28",
    "price": 990,
    "sales_point": 1501,
    "rating": 4.91,
    "rating_count": 44,
    "review_count": 0
  },
  {
    "date": "2026-04-29",
    "price": 990,
    "sales_point": 1573,
    "rating": 4.92,
    "rating_count": 48,
    "review_count": 0
  },
  {
    "date": "2026-04-30",
    "price": 990,
    "sales_point": 1597,
    "rating": 4.92,
    "rating_count": 49,
    "review_count": 0
  },
  {
    "date": "2026-05-01",
    "price": 990,
    "sales_point": 1614,
    "rating": 4.92,
    "rating_count": 50,
    "review_count": 0
  },
  {
    "date": "2026-05-02",
    "price": 990,
    "sales_point": 1751,
    "rating": 4.9,
    "rating_count": 60,
    "review_count": 0
  },
  {
    "date": "2026-05-04",
    "price": 990,
    "sales_point": 1859,
    "rating": 4.9,
    "rating_count": 67,
    "review_count": 0
  },
  {
    "date": "2026-05-05",
    "price": 990,
    "sales_point": 1889,
    "rating": 4.89,
    "rating_count": 70,
    "review_count": 0
  },
  {
    "date": "2026-05-06",
    "price": 990,
    "sales_point": 1937,
    "rating": 4.84,
    "rating_count": 74,
    "review_count": 0
  },
  {
    "date": "2026-05-07",
    "price": 990,
    "sales_point": 1999,
    "rating": 4.83,
    "rating_count": 78,
    "review_count": 0
  },
  {
    "date": "2026-05-08",
    "price": 990,
    "sales_point": 2011,
    "rating": 4.83,
    "rating_count": 78,
    "review_count": 0
  },
  {
    "date": "2026-05-09",
    "price": 990,
    "sales_point": 2031,
    "rating": 4.84,
    "rating_count": 81,
    "review_count": 0
  },
  {
    "date": "2026-05-10",
    "price": 990,
    "sales_point": 2034,
    "rating": 4.84,
    "rating_count": 81,
    "review_count": 0
  }
]