[
  {
    "date": "2026-07-17",
    "price": 3080,
    "sales_point": 162,
    "rating": null,
    "rating_count": null,
    "review_count": 0
  },
  {
    "date": "2026-07-18",
    "price": 3080,
    "sales_point": 278,
    "rating": 3.63,
    "rating_count": 8,
    "review_count": 0
  },
  {
    "date": "2026-07-19",
    "price": 3080,
    "sales_point": 334,
    "rating": 3.5,
    "rating_count": 10,
    "review_count": 0
  },
  {
    "date": "2026-07-20",
    "price": 3080,
    "sales_point": 392,
    "rating": 3.5,
    "rating_count": 12,
    "review_count": 0
  },
  {
    "date": "2026-07-21",
    "price": 3080,
    "sales_point": 421,
    "rating": 3.63,
    "rating_count": 16,
    "review_count": 0
  },
  {
    "date": "2026-07-22",
    "price": 3080,
    "sales_point": 439,
    "rating": 3.5,
    "rating_count": 18,
    "review_count": 0
  },
  {
    "date": "2026-07-23",
    "price": 3080,
    "sales_point": 455,
    "rating": 3.71,
    "rating_count": 21,
    "review_count": 0
  },
  {
    "date": "2026-07-24",
    "price": 3080,
    "sales_point": 457,
    "rating": 3.71,
    "rating_count": 21,
    "review_count": 0
  }
]