[
  {
    "date": "2026-01-03",
    "price": 1144,
    "sales_point": 37,
    "rating": null,
    "rating_count": null,
    "review_count": 0
  },
  {
    "date": "2026-01-04",
    "price": 1144,
    "sales_point": 67,
    "rating": 4.63,
    "rating_count": 8,
    "review_count": 1
  },
  {
    "date": "2026-01-05",
    "price": 1144,
    "sales_point": 88,
    "rating": 4.67,
    "rating_count": 9,
    "review_count": 1
  },
  {
    "date": "2026-01-06",
    "price": 1144,
    "sales_point": 98,
    "rating": 4.7,
    "rating_count": 10,
    "review_count": 1
  },
  {
    "date": "2026-01-07",
    "price": 1144,
    "sales_point": 113,
    "rating": 4.7,
    "rating_count": 10,
    "review_count": 1
  },
  {
    "date": "2026-01-08",
    "price": 1144,
    "sales_point": 121,
    "rating": 4.7,
    "rating_count": 10,
    "review_count": 1
  },
  {
    "date": "2026-01-09",
    "price": 1144,
    "sales_point": 127,
    "rating": 4.46,
    "rating_count": 13,
    "review_count": 1
  },
  {
    "date": "2026-01-10",
    "price": 1144,
    "sales_point": 134,
    "rating": 4.5,
    "rating_count": 14,
    "review_count": 1
  },
  {
    "date": "2026-01-11",
    "price": 1144,
    "sales_point": 147,
    "rating": 4.59,
    "rating_count": 17,
    "review_count": 1
  },
  {
    "date": "2026-01-12",
    "price": 1144,
    "sales_point": 155,
    "rating": 4.56,
    "rating_count": 18,
    "review_count": 1
  },
  {
    "date": "2026-01-13",
    "price": 1144,
    "sales_point": 163,
    "rating": 4.56,
    "rating_count": 18,
    "review_count": 1
  },
  {
    "date": "2026-01-14",
    "price": 1144,
    "sales_point": 164,
    "rating": 4.53,
    "rating_count": 19,
    "review_count": 1
  },
  {
    "date": "2026-01-15",
    "price": 1144,
    "sales_point": 166,
    "rating": 4.52,
    "rating_count": 21,
    "review_count": 1
  },
  {
    "date": "2026-01-16",
    "price": 1144,
    "sales_point": 176,
    "rating": 4.52,
    "rating_count": 21,
    "review_count": 1
  }
]