[
  {
    "date": "2025-11-14",
    "price": 880,
    "sales_point": 1283
  },
  {
    "date": "2025-11-15",
    "price": 880,
    "sales_point": 2288
  },
  {
    "date": "2025-11-16",
    "price": 880,
    "sales_point": 3152
  },
  {
    "date": "2025-11-17",
    "price": 880,
    "sales_point": 3722
  },
  {
    "date": "2025-11-18",
    "price": 880,
    "sales_point": 4228
  },
  {
    "date": "2025-11-19",
    "price": 880,
    "sales_point": 4593
  },
  {
    "date": "2025-11-20",
    "price": 880,
    "sales_point": 4962
  },
  {
    "date": "2025-11-21",
    "price": 880,
    "sales_point": 5206
  },
  {
    "date": "2025-11-22",
    "price": 880,
    "sales_point": 5461
  },
  {
    "date": "2025-11-23",
    "price": 880,
    "sales_point": 5626
  },
  {
    "date": "2025-11-24",
    "price": 880,
    "sales_point": 5789
  },
  {
    "date": "2025-11-25",
    "price": 880,
    "sales_point": 5917
  },
  {
    "date": "2025-11-26",
    "price": 880,
    "sales_point": 6055
  },
  {
    "date": "2025-11-27",
    "price": 880,
    "sales_point": 6180
  },
  {
    "date": "2025-11-28",
    "price": 880,
    "sales_point": 6292
  },
  {
    "date": "2025-11-29",
    "price": 880,
    "sales_point": 6433
  },
  {
    "date": "2025-11-30",
    "price": 880,
    "sales_point": 6583
  },
  {
    "date": "2025-12-01",
    "price": 880,
    "sales_point": 6758
  },
  {
    "date": "2025-12-02",
    "price": 880,
    "sales_point": 6873
  },
  {
    "date": "2025-12-03",
    "price": 880,
    "sales_point": 6991
  },
  {
    "date": "2025-12-04",
    "price": 880,
    "sales_point": 7069
  },
  {
    "date": "2025-12-05",
    "price": 880,
    "sales_point": 7148
  },
  {
    "date": "2025-12-06",
    "price": 880,
    "sales_point": 7250
  },
  {
    "date": "2025-12-07",
    "price": 880,
    "sales_point": 7339
  },
  {
    "date": "2025-12-08",
    "price": 880,
    "sales_point": 7418
  }
]