[
  {
    "date": "2025-11-13",
    "price": 880,
    "sales_point": 75
  },
  {
    "date": "2025-11-14",
    "price": 880,
    "sales_point": 133
  },
  {
    "date": "2025-11-15",
    "price": 880,
    "sales_point": 172
  },
  {
    "date": "2025-11-16",
    "price": 880,
    "sales_point": 202
  },
  {
    "date": "2025-11-17",
    "price": 880,
    "sales_point": 212
  },
  {
    "date": "2025-11-18",
    "price": 880,
    "sales_point": 222
  },
  {
    "date": "2025-11-19",
    "price": 880,
    "sales_point": 239
  },
  {
    "date": "2025-11-20",
    "price": 880,
    "sales_point": 245
  },
  {
    "date": "2025-11-21",
    "price": 880,
    "sales_point": 252
  },
  {
    "date": "2025-11-22",
    "price": 880,
    "sales_point": 264
  },
  {
    "date": "2025-11-23",
    "price": 880,
    "sales_point": 273
  },
  {
    "date": "2025-11-24",
    "price": 880,
    "sales_point": 280
  },
  {
    "date": "2025-11-25",
    "price": 880,
    "sales_point": 280
  }
]