[
  {
    "date": "2026-04-22",
    "price": 990,
    "sales_point": 614,
    "rating": 5,
    "rating_count": 16,
    "review_count": 0
  },
  {
    "date": "2026-04-23",
    "price": 990,
    "sales_point": 929,
    "rating": 4.92,
    "rating_count": 25,
    "review_count": 0
  },
  {
    "date": "2026-04-24",
    "price": 990,
    "sales_point": 1140,
    "rating": 4.93,
    "rating_count": 29,
    "review_count": 0
  },
  {
    "date": "2026-04-25",
    "price": 990,
    "sales_point": 1328,
    "rating": 4.94,
    "rating_count": 31,
    "review_count": 1
  },
  {
    "date": "2026-04-26",
    "price": 990,
    "sales_point": 1517,
    "rating": 4.94,
    "rating_count": 35,
    "review_count": 1
  },
  {
    "date": "2026-04-27",
    "price": 990,
    "sales_point": 1625,
    "rating": 4.95,
    "rating_count": 43,
    "review_count": 1
  },
  {
    "date": "2026-04-28",
    "price": 990,
    "sales_point": 1700,
    "rating": 4.96,
    "rating_count": 46,
    "review_count": 1
  },
  {
    "date": "2026-04-29",
    "price": 990,
    "sales_point": 1794,
    "rating": 4.96,
    "rating_count": 49,
    "review_count": 1
  },
  {
    "date": "2026-04-30",
    "price": 990,
    "sales_point": 1854,
    "rating": 4.96,
    "rating_count": 51,
    "review_count": 1
  },
  {
    "date": "2026-05-01",
    "price": 990,
    "sales_point": 1883,
    "rating": 4.96,
    "rating_count": 51,
    "review_count": 1
  },
  {
    "date": "2026-05-02",
    "price": 990,
    "sales_point": 2148,
    "rating": 4.95,
    "rating_count": 62,
    "review_count": 1
  },
  {
    "date": "2026-05-04",
    "price": 990,
    "sales_point": 2250,
    "rating": 4.9,
    "rating_count": 70,
    "review_count": 1
  },
  {
    "date": "2026-05-05",
    "price": 990,
    "sales_point": 2274,
    "rating": 4.89,
    "rating_count": 71,
    "review_count": 1
  },
  {
    "date": "2026-05-06",
    "price": 990,
    "sales_point": 2302,
    "rating": 4.89,
    "rating_count": 71,
    "review_count": 1
  },
  {
    "date": "2026-05-07",
    "price": 990,
    "sales_point": 2352,
    "rating": 4.89,
    "rating_count": 76,
    "review_count": 1
  },
  {
    "date": "2026-05-08",
    "price": 990,
    "sales_point": 2368,
    "rating": 4.9,
    "rating_count": 78,
    "review_count": 1
  },
  {
    "date": "2026-05-09",
    "price": 990,
    "sales_point": 2390,
    "rating": 4.9,
    "rating_count": 78,
    "review_count": 1
  },
  {
    "date": "2026-05-10",
    "price": 990,
    "sales_point": 2403,
    "rating": 4.9,
    "rating_count": 80,
    "review_count": 1
  },
  {
    "date": "2026-05-11",
    "price": 990,
    "sales_point": 2431,
    "rating": 4.86,
    "rating_count": 81,
    "review_count": 1
  },
  {
    "date": "2026-05-12",
    "price": 990,
    "sales_point": 2444,
    "rating": 4.87,
    "rating_count": 84,
    "review_count": 1
  },
  {
    "date": "2026-05-13",
    "price": 990,
    "sales_point": 2461,
    "rating": 4.87,
    "rating_count": 85,
    "review_count": 1
  },
  {
    "date": "2026-05-14",
    "price": 990,
    "sales_point": 2474,
    "rating": 4.87,
    "rating_count": 85,
    "review_count": 1
  },
  {
    "date": "2026-05-15",
    "price": 990,
    "sales_point": 2481,
    "rating": 4.87,
    "rating_count": 85,
    "review_count": 1
  },
  {
    "date": "2026-05-16",
    "price": 990,
    "sales_point": 2516,
    "rating": 4.87,
    "rating_count": 87,
    "review_count": 1
  },
  {
    "date": "2026-05-17",
    "price": 990,
    "sales_point": 2532,
    "rating": 4.88,
    "rating_count": 88,
    "review_count": 1
  },
  {
    "date": "2026-05-18",
    "price": 990,
    "sales_point": 2551,
    "rating": 4.88,
    "rating_count": 91,
    "review_count": 1
  },
  {
    "date": "2026-05-19",
    "price": 990,
    "sales_point": 2570,
    "rating": 4.88,
    "rating_count": 94,
    "review_count": 1
  },
  {
    "date": "2026-05-20",
    "price": 1650,
    "sales_point": 2575,
    "rating": 4.88,
    "rating_count": 95,
    "review_count": 1
  }
]