[
  {
    "date": "2025-11-05",
    "price": 968,
    "sales_point": 155
  },
  {
    "date": "2025-11-06",
    "price": 968,
    "sales_point": 329
  },
  {
    "date": "2025-11-07",
    "price": 968,
    "sales_point": 426
  },
  {
    "date": "2025-11-08",
    "price": 968,
    "sales_point": 547
  },
  {
    "date": "2025-11-09",
    "price": 968,
    "sales_point": 662
  },
  {
    "date": "2025-11-10",
    "price": 968,
    "sales_point": 728
  },
  {
    "date": "2025-11-11",
    "price": 968,
    "sales_point": 783
  },
  {
    "date": "2025-11-12",
    "price": 968,
    "sales_point": 833
  },
  {
    "date": "2025-11-13",
    "price": 968,
    "sales_point": 869
  },
  {
    "date": "2025-11-14",
    "price": 968,
    "sales_point": 893
  }
]