[
  {
    "date": "2025-09-05",
    "price": 1485,
    "sales_point": 28
  },
  {
    "date": "2025-09-06",
    "price": 1485,
    "sales_point": 67
  },
  {
    "date": "2025-09-07",
    "price": 1485,
    "sales_point": 90
  },
  {
    "date": "2025-09-08",
    "price": 1485,
    "sales_point": 110
  },
  {
    "date": "2025-09-09",
    "price": 1485,
    "sales_point": 122
  },
  {
    "date": "2025-09-10",
    "price": 1485,
    "sales_point": 125
  },
  {
    "date": "2025-09-11",
    "price": 1485,
    "sales_point": 137
  },
  {
    "date": "2025-09-12",
    "price": 1485,
    "sales_point": 147
  },
  {
    "date": "2025-09-13",
    "price": 1485,
    "sales_point": 164
  },
  {
    "date": "2025-09-14",
    "price": 1485,
    "sales_point": 178
  },
  {
    "date": "2025-09-15",
    "price": 1485,
    "sales_point": 200
  },
  {
    "date": "2025-09-16",
    "price": 1485,
    "sales_point": 207
  },
  {
    "date": "2025-09-17",
    "price": 1485,
    "sales_point": 220
  },
  {
    "date": "2025-09-18",
    "price": 1485,
    "sales_point": 232
  },
  {
    "date": "2025-09-19",
    "price": 1650,
    "sales_point": 239
  },
  {
    "date": "2025-09-20",
    "price": 1650,
    "sales_point": 250
  },
  {
    "date": "2025-09-21",
    "price": 1650,
    "sales_point": 267
  },
  {
    "date": "2025-09-22",
    "price": 1650,
    "sales_point": 278
  },
  {
    "date": "2025-09-23",
    "price": 1650,
    "sales_point": 291
  },
  {
    "date": "2025-09-24",
    "price": 1650,
    "sales_point": 293
  },
  {
    "date": "2025-09-25",
    "price": 1650,
    "sales_point": 298
  },
  {
    "date": "2025-09-26",
    "price": 1650,
    "sales_point": 305
  },
  {
    "date": "2025-09-27",
    "price": 1650,
    "sales_point": 325
  },
  {
    "date": "2025-09-28",
    "price": 1650,
    "sales_point": 353
  },
  {
    "date": "2025-09-29",
    "price": 1650,
    "sales_point": 376
  },
  {
    "date": "2025-09-30",
    "price": 1650,
    "sales_point": 391
  },
  {
    "date": "2025-10-01",
    "price": 1650,
    "sales_point": 409
  },
  {
    "date": "2025-10-02",
    "price": 1650,
    "sales_point": 428
  },
  {
    "date": "2025-10-03",
    "price": 1650,
    "sales_point": 450
  },
  {
    "date": "2025-10-04",
    "price": 1650,
    "sales_point": 460
  },
  {
    "date": "2025-10-05",
    "price": 1650,
    "sales_point": 479
  },
  {
    "date": "2025-10-06",
    "price": 1650,
    "sales_point": 491
  },
  {
    "date": "2025-10-07",
    "price": 1650,
    "sales_point": 499
  },
  {
    "date": "2025-10-08",
    "price": 1650,
    "sales_point": 513
  },
  {
    "date": "2025-10-09",
    "price": 1650,
    "sales_point": 518
  },
  {
    "date": "2025-10-10",
    "price": 1650,
    "sales_point": 535
  },
  {
    "date": "2025-10-11",
    "price": 1650,
    "sales_point": 552
  },
  {
    "date": "2025-10-12",
    "price": 1650,
    "sales_point": 560
  },
  {
    "date": "2025-10-13",
    "price": 1650,
    "sales_point": 571
  },
  {
    "date": "2025-10-14",
    "price": 1650,
    "sales_point": 580
  },
  {
    "date": "2025-10-15",
    "price": 1650,
    "sales_point": 583
  },
  {
    "date": "2025-10-16",
    "price": 1650,
    "sales_point": 588
  },
  {
    "date": "2025-10-17",
    "price": 1650,
    "sales_point": 594
  },
  {
    "date": "2025-10-18",
    "price": 1650,
    "sales_point": 600
  },
  {
    "date": "2025-10-19",
    "price": 1650,
    "sales_point": 603
  },
  {
    "date": "2025-10-20",
    "price": 1650,
    "sales_point": 611
  },
  {
    "date": "2025-10-21",
    "price": 1650,
    "sales_point": 617
  },
  {
    "date": "2025-10-22",
    "price": 1650,
    "sales_point": 621
  },
  {
    "date": "2025-10-23",
    "price": 1650,
    "sales_point": 625
  },
  {
    "date": "2025-10-24",
    "price": 1650,
    "sales_point": 628
  },
  {
    "date": "2025-10-25",
    "price": 1650,
    "sales_point": 632
  },
  {
    "date": "2025-10-26",
    "price": 1650,
    "sales_point": 641
  },
  {
    "date": "2025-10-27",
    "price": 1650,
    "sales_point": 652
  },
  {
    "date": "2025-10-28",
    "price": 1650,
    "sales_point": 658
  },
  {
    "date": "2025-10-29",
    "price": 1650,
    "sales_point": 661
  },
  {
    "date": "2025-10-30",
    "price": 1650,
    "sales_point": 663
  },
  {
    "date": "2025-10-31",
    "price": 1650,
    "sales_point": 669
  },
  {
    "date": "2025-11-01",
    "price": 1650,
    "sales_point": 678
  },
  {
    "date": "2025-11-02",
    "price": 1650,
    "sales_point": 684
  },
  {
    "date": "2025-11-03",
    "price": 1650,
    "sales_point": 694
  },
  {
    "date": "2025-11-04",
    "price": 1650,
    "sales_point": 700
  },
  {
    "date": "2025-11-05",
    "price": 1650,
    "sales_point": 704
  },
  {
    "date": "2025-11-06",
    "price": 1650,
    "sales_point": 709
  },
  {
    "date": "2025-11-07",
    "price": 1650,
    "sales_point": 716
  },
  {
    "date": "2025-11-08",
    "price": 1650,
    "sales_point": 718
  },
  {
    "date": "2025-11-09",
    "price": 1650,
    "sales_point": 729
  },
  {
    "date": "2025-11-10",
    "price": 1650,
    "sales_point": 733
  },
  {
    "date": "2025-11-11",
    "price": 1650,
    "sales_point": 737
  },
  {
    "date": "2025-11-12",
    "price": 1650,
    "sales_point": 743
  },
  {
    "date": "2025-11-13",
    "price": 1650,
    "sales_point": 749
  },
  {
    "date": "2025-11-14",
    "price": 1650,
    "sales_point": 753
  },
  {
    "date": "2025-11-15",
    "price": 1650,
    "sales_point": 757
  },
  {
    "date": "2025-11-16",
    "price": 1650,
    "sales_point": 764
  },
  {
    "date": "2025-11-17",
    "price": 1650,
    "sales_point": 769
  },
  {
    "date": "2025-11-18",
    "price": 1650,
    "sales_point": 775
  },
  {
    "date": "2025-11-19",
    "price": 1650,
    "sales_point": 775
  },
  {
    "date": "2025-11-20",
    "price": 1650,
    "sales_point": 778
  },
  {
    "date": "2025-11-21",
    "price": 1650,
    "sales_point": 784
  },
  {
    "date": "2025-11-22",
    "price": 1650,
    "sales_point": 790
  },
  {
    "date": "2025-11-23",
    "price": 1650,
    "sales_point": 797
  },
  {
    "date": "2025-11-24",
    "price": 1650,
    "sales_point": 809
  },
  {
    "date": "2025-11-25",
    "price": 1650,
    "sales_point": 812
  },
  {
    "date": "2025-11-26",
    "price": 1650,
    "sales_point": 826
  },
  {
    "date": "2025-11-27",
    "price": 1650,
    "sales_point": 830
  },
  {
    "date": "2025-11-28",
    "price": 1650,
    "sales_point": 833
  },
  {
    "date": "2025-11-29",
    "price": 1650,
    "sales_point": 838
  },
  {
    "date": "2025-11-30",
    "price": 1650,
    "sales_point": 846
  },
  {
    "date": "2025-12-01",
    "price": 1650,
    "sales_point": 851
  },
  {
    "date": "2025-12-02",
    "price": 1650,
    "sales_point": 856
  },
  {
    "date": "2025-12-03",
    "price": 1650,
    "sales_point": 857
  },
  {
    "date": "2025-12-04",
    "price": 1650,
    "sales_point": 862
  },
  {
    "date": "2025-12-05",
    "price": 1650,
    "sales_point": 866
  },
  {
    "date": "2025-12-06",
    "price": 1650,
    "sales_point": 869
  },
  {
    "date": "2025-12-07",
    "price": 1650,
    "sales_point": 878
  },
  {
    "date": "2025-12-08",
    "price": 1650,
    "sales_point": 882
  },
  {
    "date": "2025-12-09",
    "price": 1650,
    "sales_point": 885
  },
  {
    "date": "2025-12-10",
    "price": 1650,
    "sales_point": 889
  },
  {
    "date": "2025-12-11",
    "price": 1650,
    "sales_point": 891
  },
  {
    "date": "2025-12-12",
    "price": 1650,
    "sales_point": 892
  },
  {
    "date": "2025-12-13",
    "price": 1650,
    "sales_point": 898
  },
  {
    "date": "2025-12-14",
    "price": 1650,
    "sales_point": 905
  },
  {
    "date": "2025-12-15",
    "price": 1650,
    "sales_point": 910
  },
  {
    "date": "2025-12-16",
    "price": 1650,
    "sales_point": 910
  },
  {
    "date": "2025-12-17",
    "price": 1650,
    "sales_point": 913
  },
  {
    "date": "2025-12-18",
    "price": 1650,
    "sales_point": 916
  },
  {
    "date": "2025-12-19",
    "price": 1650,
    "sales_point": 921
  },
  {
    "date": "2025-12-20",
    "price": 1650,
    "sales_point": 925
  },
  {
    "date": "2025-12-21",
    "price": 1650,
    "sales_point": 927
  },
  {
    "date": "2025-12-22",
    "price": 1650,
    "sales_point": 930
  },
  {
    "date": "2025-12-23",
    "price": 1650,
    "sales_point": 931
  },
  {
    "date": "2025-12-24",
    "price": 1650,
    "sales_point": 934
  },
  {
    "date": "2025-12-25",
    "price": 1650,
    "sales_point": 940
  },
  {
    "date": "2025-12-26",
    "price": 1650,
    "sales_point": 946
  },
  {
    "date": "2025-12-27",
    "price": 1650,
    "sales_point": 951
  },
  {
    "date": "2025-12-28",
    "price": 1650,
    "sales_point": 959
  },
  {
    "date": "2025-12-29",
    "price": 1650,
    "sales_point": 960
  },
  {
    "date": "2025-12-30",
    "price": 1650,
    "sales_point": 960
  },
  {
    "date": "2025-12-31",
    "price": 1650,
    "sales_point": 961
  },
  {
    "date": "2026-01-01",
    "price": 1650,
    "sales_point": 961
  },
  {
    "date": "2026-01-02",
    "price": 1650,
    "sales_point": 964
  }
]