[
  {
    "date": "2025-09-21",
    "price": 880,
    "sales_point": 4
  },
  {
    "date": "2025-09-22",
    "price": 880,
    "sales_point": 5
  },
  {
    "date": "2025-09-23",
    "price": 880,
    "sales_point": 5
  },
  {
    "date": "2025-09-24",
    "price": 880,
    "sales_point": 5
  },
  {
    "date": "2025-09-25",
    "price": 880,
    "sales_point": 6
  },
  {
    "date": "2025-09-26",
    "price": 880,
    "sales_point": 7
  },
  {
    "date": "2025-09-27",
    "price": 880,
    "sales_point": 7
  },
  {
    "date": "2025-09-28",
    "price": 880,
    "sales_point": 7
  }
]