[
  {
    "date": "2026-01-22",
    "price": 1056,
    "sales_point": 322,
    "rating": 4.69,
    "rating_count": 13,
    "review_count": 0
  },
  {
    "date": "2026-01-23",
    "price": 1056,
    "sales_point": 510,
    "rating": 4.81,
    "rating_count": 21,
    "review_count": 0
  },
  {
    "date": "2026-01-24",
    "price": 1056,
    "sales_point": 714,
    "rating": 4.78,
    "rating_count": 27,
    "review_count": 0
  },
  {
    "date": "2026-01-25",
    "price": 1056,
    "sales_point": 843,
    "rating": 4.81,
    "rating_count": 32,
    "review_count": 0
  },
  {
    "date": "2026-01-26",
    "price": 1056,
    "sales_point": 941,
    "rating": 4.84,
    "rating_count": 38,
    "review_count": 1
  },
  {
    "date": "2026-01-27",
    "price": 1056,
    "sales_point": 1012,
    "rating": 4.75,
    "rating_count": 40,
    "review_count": 1
  },
  {
    "date": "2026-01-28",
    "price": 1056,
    "sales_point": 1088,
    "rating": 4.75,
    "rating_count": 40,
    "review_count": 1
  },
  {
    "date": "2026-01-29",
    "price": 1056,
    "sales_point": 1144,
    "rating": 4.77,
    "rating_count": 43,
    "review_count": 1
  },
  {
    "date": "2026-01-30",
    "price": 1056,
    "sales_point": 1206,
    "rating": 4.77,
    "rating_count": 44,
    "review_count": 1
  },
  {
    "date": "2026-01-31",
    "price": 1056,
    "sales_point": 1267,
    "rating": 4.73,
    "rating_count": 49,
    "review_count": 1
  },
  {
    "date": "2026-02-01",
    "price": 1056,
    "sales_point": 1365,
    "rating": 4.75,
    "rating_count": 52,
    "review_count": 1
  },
  {
    "date": "2026-02-02",
    "price": 1056,
    "sales_point": 1424,
    "rating": 4.75,
    "rating_count": 52,
    "review_count": 1
  },
  {
    "date": "2026-02-03",
    "price": 1056,
    "sales_point": 1469,
    "rating": 4.67,
    "rating_count": 57,
    "review_count": 1
  },
  {
    "date": "2026-02-04",
    "price": 1056,
    "sales_point": 1517,
    "rating": 4.68,
    "rating_count": 60,
    "review_count": 1
  },
  {
    "date": "2026-02-05",
    "price": 1320,
    "sales_point": 1539,
    "rating": 4.66,
    "rating_count": 62,
    "review_count": 1
  },
  {
    "date": "2026-02-06",
    "price": 1320,
    "sales_point": 1560,
    "rating": 4.67,
    "rating_count": 63,
    "review_count": 1
  },
  {
    "date": "2026-02-07",
    "price": 1320,
    "sales_point": 1581,
    "rating": 4.67,
    "rating_count": 64,
    "review_count": 1
  },
  {
    "date": "2026-02-08",
    "price": 1320,
    "sales_point": 1595,
    "rating": 4.69,
    "rating_count": 68,
    "review_count": 1
  },
  {
    "date": "2026-02-09",
    "price": 1320,
    "sales_point": 1608,
    "rating": 4.7,
    "rating_count": 69,
    "review_count": 1
  },
  {
    "date": "2026-02-10",
    "price": 1320,
    "sales_point": 1618,
    "rating": 4.71,
    "rating_count": 72,
    "review_count": 1
  },
  {
    "date": "2026-02-11",
    "price": 1320,
    "sales_point": 1635,
    "rating": 4.72,
    "rating_count": 75,
    "review_count": 1
  },
  {
    "date": "2026-02-12",
    "price": 1320,
    "sales_point": 1647,
    "rating": 4.72,
    "rating_count": 78,
    "review_count": 1
  }
]