[
  {
    "date": "2025-12-19",
    "price": 1430,
    "sales_point": 34,
    "rating": null,
    "rating_count": null,
    "review_count": null
  },
  {
    "date": "2025-12-20",
    "price": 1430,
    "sales_point": 64,
    "rating": null,
    "rating_count": null,
    "review_count": null
  },
  {
    "date": "2025-12-21",
    "price": 1430,
    "sales_point": 74,
    "rating": null,
    "rating_count": null,
    "review_count": null
  },
  {
    "date": "2025-12-22",
    "price": 1430,
    "sales_point": 81,
    "rating": null,
    "rating_count": null,
    "review_count": null
  },
  {
    "date": "2025-12-23",
    "price": 1430,
    "sales_point": 82,
    "rating": null,
    "rating_count": null,
    "review_count": null
  },
  {
    "date": "2025-12-24",
    "price": 1430,
    "sales_point": 82,
    "rating": null,
    "rating_count": null,
    "review_count": null
  },
  {
    "date": "2025-12-25",
    "price": 1430,
    "sales_point": 86,
    "rating": null,
    "rating_count": null,
    "review_count": null
  },
  {
    "date": "2025-12-26",
    "price": 1430,
    "sales_point": 88,
    "rating": null,
    "rating_count": null,
    "review_count": null
  },
  {
    "date": "2025-12-27",
    "price": 1430,
    "sales_point": 88,
    "rating": null,
    "rating_count": null,
    "review_count": null
  },
  {
    "date": "2025-12-28",
    "price": 1430,
    "sales_point": 88,
    "rating": null,
    "rating_count": null,
    "review_count": null
  },
  {
    "date": "2025-12-29",
    "price": 1430,
    "sales_point": 90,
    "rating": null,
    "rating_count": null,
    "review_count": null
  },
  {
    "date": "2025-12-30",
    "price": 1430,
    "sales_point": 91,
    "rating": null,
    "rating_count": null,
    "review_count": null
  },
  {
    "date": "2025-12-31",
    "price": 1430,
    "sales_point": 93,
    "rating": null,
    "rating_count": null,
    "review_count": null
  },
  {
    "date": "2026-01-01",
    "price": 1430,
    "sales_point": 93,
    "rating": null,
    "rating_count": null,
    "review_count": null
  },
  {
    "date": "2026-01-02",
    "price": 1430,
    "sales_point": 96,
    "rating": 3.71,
    "rating_count": 7,
    "review_count": 0
  },
  {
    "date": "2026-01-03",
    "price": 1430,
    "sales_point": 98,
    "rating": 3.71,
    "rating_count": 7,
    "review_count": 0
  },
  {
    "date": "2026-01-04",
    "price": 1430,
    "sales_point": 100,
    "rating": 3.75,
    "rating_count": 8,
    "review_count": 0
  },
  {
    "date": "2026-01-05",
    "price": 1430,
    "sales_point": 101,
    "rating": 3.75,
    "rating_count": 8,
    "review_count": 0
  },
  {
    "date": "2026-01-06",
    "price": 1430,
    "sales_point": 102,
    "rating": 3.67,
    "rating_count": 9,
    "review_count": 0
  },
  {
    "date": "2026-01-07",
    "price": 1430,
    "sales_point": 103,
    "rating": 3.67,
    "rating_count": 9,
    "review_count": 0
  },
  {
    "date": "2026-01-08",
    "price": 1430,
    "sales_point": 103,
    "rating": 3.67,
    "rating_count": 9,
    "review_count": 0
  },
  {
    "date": "2026-01-09",
    "price": 1430,
    "sales_point": 103,
    "rating": 3.56,
    "rating_count": 9,
    "review_count": 0
  },
  {
    "date": "2026-01-10",
    "price": 1430,
    "sales_point": 103,
    "rating": 3.56,
    "rating_count": 9,
    "review_count": 0
  },
  {
    "date": "2026-01-11",
    "price": 1430,
    "sales_point": 103,
    "rating": 3.56,
    "rating_count": 9,
    "review_count": 0
  }
]